[{"revisionId":607214,"songId":15533,"description":"Changes according to the original track\r\n(via editor)","createdAt":"2023-08-18T17:40:41.000Z","source":"https://gp.songsterr.com/58977764.gp","personId":2550963,"person":"VitaliySR","title":"Mi Lupita","artist":"Pito Perez","tracksCount":5,"reports":[],"commentsCount":0},{"revisionId":607209,"songId":15533,"description":"Better version","createdAt":"2023-08-18T17:24:33.000Z","source":"https://gp.songsterr.com/58977297.gp5","personId":2550963,"person":"VitaliySR","title":"Mi Lupita","artist":"Pito Perez","tracksCount":5,"reports":[],"commentsCount":0},{"revisionId":17408,"songId":15533,"description":"Initial revision","createdAt":"2009-01-18T19:49:58.000Z","source":"https://gp.songsterr.com/3628881.gp4","personId":33,"person":"Leland","title":"Mi Lupita","artist":"Pito Perez","tracksCount":2,"reports":[],"commentsCount":0}]