[{"revisionId":556991,"songId":22187,"description":"markers and more guitar parts and updated drums","createdAt":"2023-03-22T22:40:28.000Z","source":"https://gp.songsterr.com/55997141.gp5","personId":2496052,"person":"fentooozler","title":"Strings","artist":"Blink-182","tracksCount":5,"reports":[],"commentsCount":0},{"revisionId":24944,"songId":22187,"description":"Initial revision","createdAt":"2009-02-14T21:19:22.000Z","source":"https://gp.songsterr.com/3638117.gp4","personId":703,"person":"ruvik","title":"Strings","artist":"Blink-182","tracksCount":4,"reports":[],"commentsCount":0}]