[{"revisionId":610658,"songId":24735,"description":"Empty bars added to better sync with the original track\r\n(via editor)","createdAt":"2023-08-27T21:03:57.000Z","source":"https://gp.songsterr.com/59149890.gp","personId":2550963,"person":"VitaliySR","title":"Rats In The Cellar","artist":"Aerosmith","tracksCount":4,"reports":[],"commentsCount":0},{"revisionId":42267,"songId":24735,"description":"Initial revision","createdAt":"2009-09-16T12:40:45.000Z","source":"https://gp.songsterr.com/3641655.gp3","personId":145787,"person":"Leonard","title":"Rats In The Cellar","artist":"Aerosmith","tracksCount":4,"reports":[],"commentsCount":0}]