[{"revisionId":388069,"songId":26325,"description":"fixed the bass","createdAt":"2019-11-11T15:20:28.000Z","source":"https://gp.songsterr.com/40554477.gp5","personId":1920545,"person":"snoregon","title":"Return Of The Darkness And Evil","artist":"Bathory","tracksCount":3,"reports":[{"kind":"errors","summary":"The third power chord of the main riff is incorrect. It should be an A# instead of B"}],"commentsCount":0},{"revisionId":388068,"songId":26325,"description":"distortion is a go, i think","createdAt":"2019-11-11T15:18:22.000Z","source":"https://gp.songsterr.com/40554476.gp5","personId":1920545,"person":"snoregon","title":"Return Of The Darkness And Evil","artist":"Bathory","tracksCount":3,"reports":[],"commentsCount":0},{"revisionId":388066,"songId":26325,"description":"fixed the tuning, the tempo and notation, added distortion, added markers, fixed the outro, and one tiny other error","createdAt":"2019-11-11T15:01:32.000Z","source":"https://gp.songsterr.com/40554006.gp5","personId":1920545,"person":"snoregon","title":"Return Of The Darkness And Evil","artist":"Bathory","tracksCount":3,"reports":[],"commentsCount":0},{"revisionId":388064,"songId":26325,"description":"fixed the tuning, the tempo and notation, added distortion, added markers, fixed the outro","createdAt":"2019-11-11T14:59:45.000Z","source":"https://gp.songsterr.com/40554004.gp5","personId":1920545,"person":"snoregon","title":"Return Of The Darkness And Evil","artist":"Bathory","tracksCount":3,"reports":[],"commentsCount":0},{"revisionId":315469,"songId":26325,"description":"Initial revision","createdAt":"2016-11-20T08:21:22.000Z","source":"https://gp.songsterr.com/23655352.gp3","personId":145787,"person":"Leonard","title":"Return Of The Darkness And Evil","artist":"Bathory","tracksCount":3,"reports":[],"commentsCount":0}]