[{"revisionId":572035,"songId":28672,"description":"bar editing\r\n(via editor)","createdAt":"2023-05-12T15:43:06.000Z","source":"https://gp.songsterr.com/56960177.gp","personId":2233818,"person":"Oleg Kalbenko","title":"Cotton Fields","artist":"Creedence Clearwater Revival","tracksCount":3,"reports":[],"commentsCount":0},{"revisionId":43788,"songId":28672,"description":"Initial revision","createdAt":"2009-09-17T07:38:54.000Z","source":"https://gp.songsterr.com/3646693.gp3","personId":145787,"person":"Leonard","title":"Cotton Fields","artist":"Creedence Clearwater Revival","tracksCount":3,"reports":[],"commentsCount":0}]