[{"revisionId":575755,"songId":29030,"description":"added bars and repeats\r\n(via editor)","createdAt":"2023-05-24T09:22:15.000Z","source":"https://gp.songsterr.com/57168568.gp","personId":2587083,"person":"Vitgit","title":"Hang On To Yourself","artist":"David Bowie","tracksCount":7,"reports":[],"commentsCount":0},{"revisionId":424610,"songId":29030,"description":"-Moved around the fingering on the bass track.\n\n-Moved a 2/4 bar to keep the phrases consistent.","createdAt":"2020-12-01T02:10:40.000Z","source":"https://gp.songsterr.com/43976967.gp5","personId":1872991,"person":"WolfPatt","title":"Hang On To Yourself","artist":"David Bowie","tracksCount":7,"reports":[],"commentsCount":0},{"revisionId":292910,"songId":29030,"description":"corrected bass, added drums","createdAt":"2016-10-25T02:54:31.000Z","source":"https://gp.songsterr.com/21659297.gp5","personId":52710,"person":"HauntedPJ","title":"Hang On To Yourself","artist":"David Bowie","tracksCount":7,"reports":[],"commentsCount":0}]