[{"revisionId":417565,"songId":34055,"description":"música retirada do songbook original da banda","createdAt":"2020-09-27T07:07:31.000Z","source":"https://gp.songsterr.com/43338178.gp5","personId":2115370,"person":"Deleted user","title":"Be Quick Or Be Dead","artist":"Iron Maiden","tracksCount":5,"reports":[],"commentsCount":0},{"revisionId":403477,"songId":34055,"description":"Added:\nPalm mutes\nJanick Gers and Dave Murray in separate track\nOverdub track\nDave's overdub in his solo\nNametags\nSection headers\nand info about this song","createdAt":"2020-05-06T10:03:19.000Z","source":"https://gp.songsterr.com/41996516.gp5","personId":1962876,"person":"Austin Clark","title":"Be Quick Or Be Dead","artist":"Iron Maiden","tracksCount":8,"reports":[],"commentsCount":0},{"revisionId":235970,"songId":34055,"description":"Made drum track more clearly (removed pauses where they was useless) and set drums positions on lines to have better visual.","createdAt":"2014-03-25T20:47:48.000Z","source":"https://gp.songsterr.com/15291988.gp3","personId":624365,"person":"Valdafaluk","title":"Be Quick Or Be Dead","artist":"Iron Maiden","tracksCount":7,"reports":[],"commentsCount":0}]