[{"revisionId":630168,"songId":393669,"description":"Added missed pause bar\n(via editor)","createdAt":"2023-10-17T17:45:35.835Z","source":"https://gp.songsterr.com/export.309909.gp","personId":2587078,"person":"Evgeny","title":"Sadness And Hate (2013)","artist":"Wintersun","tracksCount":8,"reports":[],"commentsCount":0},{"revisionId":630150,"songId":393669,"description":"Re-render","createdAt":"2023-10-17T17:03:53.634Z","source":"https://gp.songsterr.com/25358835.210445.gp","personId":2587078,"person":"Evgeny","title":"Sadness And Hate (2013)","artist":"Wintersun","tracksCount":8,"reports":[],"commentsCount":0},{"revisionId":330034,"songId":393669,"description":"Initial revision","createdAt":"2017-04-15T17:54:29.000Z","source":"https://gp.songsterr.com/25358835.gp5","personId":579070,"person":"NeoCat1993","title":"Sadness And Hate (2013)","artist":"Wintersun","tracksCount":8,"reports":[],"commentsCount":0}]