[{"revisionId":591782,"songId":3960,"description":"Tab expanded; empty bars added to better sync with the original track\r\n(via editor)","createdAt":"2023-07-09T11:58:18.000Z","source":"https://gp.songsterr.com/58070100.gp","personId":2550963,"person":"VitaliySR","title":"Butelki Z Benzyną I Kamienie","artist":"Cool Kids Of Death","tracksCount":5,"reports":[],"commentsCount":0},{"revisionId":6404,"songId":3960,"description":"Initial revision","createdAt":"2008-12-13T20:51:14.000Z","source":"https://gp.songsterr.com/3612775.gp4","personId":33,"person":"Leland","title":"Butelki Z Benzyną I Kamienie","artist":"Cool Kids Of Death","tracksCount":5,"reports":[],"commentsCount":0}]