[{"revisionId":579106,"songId":422049,"description":"Minor changes according to the otiginal track\r\n(via editor)","createdAt":"2023-06-03T20:37:42.000Z","source":"https://gp.songsterr.com/57354317.gp","personId":2550963,"person":"VitaliySR","title":"Estrechez De Corazón","artist":"Los Prisioneros","tracksCount":7,"reports":[],"commentsCount":0},{"revisionId":290715,"songId":422049,"description":"Initial revision","createdAt":"2016-10-24T01:44:34.000Z","source":"https://gp.songsterr.com/21535509.gp5","personId":755000,"person":"Dmitry Enikeev","title":"Estrechez De Corazón","artist":"Los Prisioneros","tracksCount":7,"reports":[],"commentsCount":0}]