[{"revisionId":356967,"songId":443741,"description":"afdsafsdfasdf","createdAt":"2018-07-04T06:58:56.000Z","source":"https://gp.songsterr.com/37597596.gp5","personId":1405918,"person":"Z A L G O","title":"Testing me me","artist":"Yah Yeeterson","tracksCount":4,"reports":[],"commentsCount":0},{"revisionId":356965,"songId":443741,"description":"asdfasdfasdfasdfasdfasdf","createdAt":"2018-07-04T06:53:43.000Z","source":"https://gp.songsterr.com/37597302.gp5","personId":1405918,"person":"Z A L G O","title":"Testing me me","artist":"Yah Yeeterson","tracksCount":4,"reports":[],"commentsCount":0},{"revisionId":356963,"songId":443741,"description":"Initial revision","createdAt":"2018-07-04T06:47:24.000Z","source":"https://gp.songsterr.com/37597098.gp5","personId":1405918,"person":"Z A L G O","title":"Testing me me","artist":"Yah Yeeterson","tracksCount":4,"reports":[],"commentsCount":0}]