[{"revisionId":367811,"songId":448697,"description":"Updated the beat","createdAt":"2019-01-05T17:15:15.000Z","source":"https://gp.songsterr.com/38631176.gp5","personId":237970,"person":"Striking Cobra","title":"Drop D Riff #1","artist":"Nathaneil R. Peet","tracksCount":4,"reports":[],"commentsCount":0},{"revisionId":367810,"songId":448697,"description":"Updated some of the drums and the riff","createdAt":"2019-01-05T17:11:03.000Z","source":"https://gp.songsterr.com/38630951.gp5","personId":237970,"person":"Striking Cobra","title":"Drop D Riff #1","artist":"Nathaneil R. Peet","tracksCount":4,"reports":[],"commentsCount":0},{"revisionId":367808,"songId":448697,"description":"Initial revision","createdAt":"2019-01-05T17:01:38.000Z","source":"https://gp.songsterr.com/38630831.gp5","personId":237970,"person":"Striking Cobra","title":"Drop D Riff #1","artist":"Nathaneil R. Peet","tracksCount":4,"reports":[],"commentsCount":0}]