[{"revisionId":499439,"songId":457556,"description":"Added track","createdAt":"2022-06-24T23:45:17.790Z","source":"https://gp.songsterr.com/50852718.gp5","personId":1611047,"person":"Daarii","title":"You're Not Here Ver.3","artist":"Akira Yamaoka","tracksCount":7,"reports":[],"commentsCount":0},{"revisionId":387294,"songId":457556,"description":"Initial revision","createdAt":"2019-11-01T05:56:54.000Z","source":"https://gp.songsterr.com/40481524.gp5","personId":1611047,"person":"Daarii","title":"You're Not Here Ver.3","artist":"Akira Yamaoka","tracksCount":6,"reports":[],"commentsCount":0}]