[{"revisionId":391188,"songId":459504,"description":"gfgegg","createdAt":"2019-12-20T14:01:53.000Z","source":"https://gp.songsterr.com/40848718.gp5","personId":1916339,"person":"Dmitry Zulfigarov","title":"Riffs (Dropped B)","artist":"Leviafans's Death","tracksCount":4,"reports":[],"commentsCount":0},{"revisionId":391098,"songId":459504,"description":"Initial revision","createdAt":"2019-12-19T16:46:10.000Z","source":"https://gp.songsterr.com/40839998.gp5","personId":1916339,"person":"Dmitry Zulfigarov","title":"Riffs (Dropped B)","artist":"Leviafans's Death","tracksCount":4,"reports":[],"commentsCount":0}]