[{"revisionId":604486,"songId":460189,"description":"Minor changes\r\n(via editor)","createdAt":"2023-08-11T16:20:36.000Z","source":"https://gp.songsterr.com/58819543.gp","personId":2182125,"person":"Ivan","title":"Zsákmányállat","artist":"Kispál és a Borz","tracksCount":4,"reports":[],"commentsCount":0},{"revisionId":408143,"songId":460189,"description":"Többi hangszer","createdAt":"2020-06-25T08:53:49.000Z","source":"https://gp.songsterr.com/42455077.gp5","personId":1049727,"person":"marcibox","title":"Zsákmányállat","artist":"Kispál és a Borz","tracksCount":4,"reports":[],"commentsCount":0},{"revisionId":392499,"songId":460189,"description":"Initial revision","createdAt":"2020-01-07T18:34:44.000Z","source":"https://gp.songsterr.com/40979036.gp5","personId":1947019,"person":"danielsuli","title":"Zsákmányállat","artist":"Kispál és a Borz","tracksCount":1,"reports":[],"commentsCount":0}]