[{"revisionId":395936,"songId":461872,"description":"What the hell?","createdAt":"2020-02-18T19:24:27.000Z","source":"https://gp.songsterr.com/41323886.gp5","personId":1535556,"person":"Zialism1","title":"What the hell?","artist":"Martin R","tracksCount":1,"reports":[],"commentsCount":0},{"revisionId":395935,"songId":461872,"description":"What the hell?","createdAt":"2020-02-18T19:18:55.000Z","source":"https://gp.songsterr.com/41323837.gp5","personId":1535556,"person":"Zialism1","title":"What the hell?","artist":"Martin R","tracksCount":1,"reports":[],"commentsCount":0},{"revisionId":395934,"songId":461872,"description":"What the hell?","createdAt":"2020-02-18T19:18:37.000Z","source":"https://gp.songsterr.com/41323836.gp5","personId":1535556,"person":"Zialism1","title":"What the hell?","artist":"Martin R","tracksCount":1,"reports":[],"commentsCount":0},{"revisionId":395933,"songId":461872,"description":"Initial revision","createdAt":"2020-02-18T19:15:10.000Z","source":"https://gp.songsterr.com/41323733.gp5","personId":1535556,"person":"Zialism1","title":"What the hell?","artist":"Martin R","tracksCount":1,"reports":[],"commentsCount":0}]