[{"revisionId":404352,"songId":465878,"description":"Changed bass, fixed errors","createdAt":"2020-05-15T20:34:43.000Z","source":"https://gp.songsterr.com/42080832.gp5","personId":2012839,"person":"Alexander Lusty","title":"P1","artist":"Luz","tracksCount":3,"reports":[],"commentsCount":0},{"revisionId":404351,"songId":465878,"description":"Added drums and bass","createdAt":"2020-05-15T20:16:19.000Z","source":"https://gp.songsterr.com/42080757.gp5","personId":2012839,"person":"Alexander Lusty","title":"P1","artist":"Luz","tracksCount":3,"reports":[],"commentsCount":0},{"revisionId":404155,"songId":465878,"description":"Repeats changed","createdAt":"2020-05-13T15:08:44.000Z","source":"https://gp.songsterr.com/42061726.gp5","personId":2012839,"person":"Alexander Lusty","title":"P1","artist":"Luz","tracksCount":2,"reports":[],"commentsCount":0},{"revisionId":404153,"songId":465878,"description":"2nd riff","createdAt":"2020-05-13T15:00:47.000Z","source":"https://gp.songsterr.com/42061676.gp5","personId":2012839,"person":"Alexander Lusty","title":"P1","artist":"Luz","tracksCount":2,"reports":[],"commentsCount":0},{"revisionId":404147,"songId":465878,"description":"Initial revision","createdAt":"2020-05-13T14:07:57.000Z","source":"https://gp.songsterr.com/42061259.gp5","personId":2012839,"person":"Alexander Lusty","title":"P1","artist":"Luz","tracksCount":2,"reports":[],"commentsCount":0}]