[{"revisionId":503264,"songId":47296,"description":"Toms","createdAt":"2022-07-18T00:25:48.542Z","source":"https://gp.songsterr.com/51218275.gp5","personId":1390559,"person":"Noopy","title":"Mommy Can I Go Out And Kill Tonight","artist":"Misfits","tracksCount":5,"reports":[],"commentsCount":0},{"revisionId":503253,"songId":47296,"description":"added toms","createdAt":"2022-07-17T23:13:18.118Z","source":"https://gp.songsterr.com/51216354.gp5","personId":1390559,"person":"Noopy","title":"Mommy Can I Go Out And Kill Tonight","artist":"Misfits","tracksCount":5,"reports":[],"commentsCount":0},{"revisionId":502430,"songId":47296,"description":"Added the overdubs","createdAt":"2022-07-14T00:42:51.888Z","source":"https://gp.songsterr.com/51151487.gp5","personId":1390559,"person":"Noopy","title":"Mommy Can I Go Out And Kill Tonight","artist":"Misfits","tracksCount":5,"reports":[],"commentsCount":0},{"revisionId":501452,"songId":47296,"description":"bpm","createdAt":"2022-07-07T19:00:59.017Z","source":"https://gp.songsterr.com/51057786.gp5","personId":1390559,"person":"Noopy","title":"Mommy Can I Go Out And Kill Tonight","artist":"Misfits","tracksCount":4,"reports":[],"commentsCount":0},{"revisionId":205060,"songId":47296,"description":"Fixed the intro,it's A5-A5-C5 x3 not A5-A5-C5-C5 x 3\nFixed the bass.","createdAt":"2012-11-10T20:22:58.000Z","source":"https://gp.songsterr.com/11802056.gp5","personId":334417,"person":"Gabbo","title":"Mommy Can I Go Out And Kill Tonight","artist":"Misfits","tracksCount":3,"reports":[],"commentsCount":0}]