[{"revisionId":422810,"songId":474922,"description":"fixed the ending","createdAt":"2020-11-13T06:41:42.000Z","source":"https://gp.songsterr.com/43810025.gp5","personId":1954627,"person":"mr_brapman","title":"a little song =)","artist":"Me","tracksCount":2,"reports":[],"commentsCount":0},{"revisionId":422789,"songId":474922,"description":"added drums","createdAt":"2020-11-13T02:14:50.000Z","source":"https://gp.songsterr.com/43807941.gp5","personId":1954627,"person":"mr_brapman","title":"a little song =)","artist":"Me","tracksCount":2,"reports":[],"commentsCount":0},{"revisionId":422698,"songId":474922,"description":"Initial revision","createdAt":"2020-11-12T08:02:39.000Z","source":"https://gp.songsterr.com/43799467.gp5","personId":1954627,"person":"mr_brapman","title":"a little song =)","artist":"Me","tracksCount":1,"reports":[],"commentsCount":0}]