[{"revisionId":424134,"songId":475519,"description":"Demo song","createdAt":"2020-11-26T03:54:05.000Z","source":"https://gp.songsterr.com/43935239.gp5","personId":1411847,"person":"Zialism","title":"demo song","artist":"A Negative Regenerative Pheasant","tracksCount":1,"reports":[],"commentsCount":0},{"revisionId":423930,"songId":475519,"description":"Initial revision","createdAt":"2020-11-24T02:33:26.000Z","source":"https://gp.songsterr.com/43918019.gp5","personId":1411847,"person":"Zialism","title":"demo song","artist":"A Negative Regenerative Pheasant","tracksCount":1,"reports":[],"commentsCount":0}]