[{"revisionId":438329,"songId":482190,"description":"Fixed verse snare","createdAt":"2021-04-07T02:05:28.000Z","source":"https://gp.songsterr.com/45252641.gp5","personId":1112031,"person":"Emilio Bartning","title":"Deceiver","artist":"Soen","tracksCount":7,"reports":[],"commentsCount":0},{"revisionId":438328,"songId":482190,"description":"Improved Drums","createdAt":"2021-04-07T01:56:00.000Z","source":"https://gp.songsterr.com/45252470.gp5","personId":1112031,"person":"Emilio Bartning","title":"Deceiver","artist":"Soen","tracksCount":7,"reports":[],"commentsCount":0},{"revisionId":438229,"songId":482190,"description":"Fixe Drumms","createdAt":"2021-04-06T07:16:48.000Z","source":"https://gp.songsterr.com/45242869.gp5","personId":1112031,"person":"Emilio Bartning","title":"Deceiver","artist":"Soen","tracksCount":7,"reports":[],"commentsCount":0},{"revisionId":438228,"songId":482190,"description":"Fixed Drums","createdAt":"2021-04-06T07:14:21.000Z","source":"https://gp.songsterr.com/45242868.gp5","personId":1112031,"person":"Emilio Bartning","title":"Deceiver","artist":"Soen","tracksCount":7,"reports":[],"commentsCount":0},{"revisionId":438223,"songId":482190,"description":"Fixed drums (again)","createdAt":"2021-04-06T06:37:18.000Z","source":"https://gp.songsterr.com/45242546.gp5","personId":1112031,"person":"Emilio Bartning","title":"Deceiver","artist":"Soen","tracksCount":7,"reports":[],"commentsCount":0},{"revisionId":438222,"songId":482190,"description":"Fixed Drums hopefully","createdAt":"2021-04-06T06:23:13.000Z","source":"https://gp.songsterr.com/45242373.gp5","personId":1112031,"person":"Emilio Bartning","title":"Deceiver","artist":"Soen","tracksCount":7,"reports":[],"commentsCount":0},{"revisionId":438221,"songId":482190,"description":"Fixed drums","createdAt":"2021-04-06T06:00:26.000Z","source":"https://gp.songsterr.com/45242202.gp5","personId":1112031,"person":"Emilio Bartning","title":"Deceiver","artist":"Soen","tracksCount":7,"reports":[],"commentsCount":0},{"revisionId":438090,"songId":482190,"description":"Initial revision","createdAt":"2021-04-05T01:37:19.000Z","source":"https://gp.songsterr.com/45232290.gp5","personId":1112031,"person":"Emilio Bartning","title":"Deceiver","artist":"Soen","tracksCount":7,"reports":[],"commentsCount":0}]