[{"revisionId":456940,"songId":484493,"description":"Tempo fixed, time signature in compass 27 fixed.","createdAt":"2021-09-03T18:19:18.000Z","source":"https://gp.songsterr.com/46927156.gp5","personId":2167853,"person":"Michi feroz","title":"Young Girl Illusion (Necro-fantasy/A Maiden's Illusionary Funeral cover)","artist":"Sing R. Sing!","tracksCount":5,"reports":[],"commentsCount":0},{"revisionId":456833,"songId":484493,"description":"Fixed time signature, fixed instruments (all the recorder tracks are tuned one octave higher), fixed harmony. \nPD: Album released on 13-10-2010, the tab didn't save the info. The song is called just Girl Illusion.","createdAt":"2021-09-03T01:25:13.000Z","source":"https://gp.songsterr.com/46920402.gp5","personId":2167853,"person":"Michi feroz","title":"Young Girl Illusion (Necro-fantasy/A Maiden's Illusionary Funeral cover)","artist":"Sing R. Sing!","tracksCount":5,"reports":[],"commentsCount":0},{"revisionId":452401,"songId":484493,"description":"Song data updated.","createdAt":"2021-08-04T19:15:28.000Z","source":"https://gp.songsterr.com/46531690.gp5","personId":2167853,"person":"Michi feroz","title":"Young Girl Illusion (Necro-fantasy/A Maiden's Illusionary Funeral cover)","artist":"Sing R. Sing!","tracksCount":5,"reports":[],"commentsCount":0},{"revisionId":442945,"songId":484493,"description":"Initial revision","createdAt":"2021-05-16T17:13:30.000Z","source":"https://gp.songsterr.com/45658727.gp5","personId":2167853,"person":"Michi feroz","title":"Young Girl Illusion (Necro-fantasy/A Maiden's Illusionary Funeral cover)","artist":"Sing R. Sing!","tracksCount":5,"reports":[],"commentsCount":0}]