[{"revisionId":446091,"songId":485907,"description":"One more verison (shitty drums)","createdAt":"2021-06-12T10:47:29.000Z","source":"https://gp.songsterr.com/45937188.gp5","personId":2162379,"person":"Doomlessnight","title":"Maska","artist":"Den' Herni","tracksCount":5,"reports":[],"commentsCount":0},{"revisionId":446089,"songId":485907,"description":"ьфылф","createdAt":"2021-06-12T10:41:39.000Z","source":"https://gp.songsterr.com/45936870.gp5","personId":2162379,"person":"Doomlessnight","title":"Maska","artist":"Den' Herni","tracksCount":5,"reports":[],"commentsCount":0},{"revisionId":446038,"songId":485907,"description":"ваываыва","createdAt":"2021-06-11T20:50:26.000Z","source":"https://gp.songsterr.com/45932522.gp5","personId":2162379,"person":"Doomlessnight","title":"Maska","artist":"Den' Herni","tracksCount":5,"reports":[],"commentsCount":0},{"revisionId":446037,"songId":485907,"description":"Voie and ect","createdAt":"2021-06-11T20:23:09.000Z","source":"https://gp.songsterr.com/45932399.gp5","personId":2162379,"person":"Doomlessnight","title":"Maska","artist":"Den' Herni","tracksCount":5,"reports":[],"commentsCount":0},{"revisionId":446032,"songId":485907,"description":"Initial revision","createdAt":"2021-06-11T19:28:06.000Z","source":"https://gp.songsterr.com/45931963.gp5","personId":2162379,"person":"Doomlessnight","title":"Maska","artist":"Den' Herni","tracksCount":4,"reports":[],"commentsCount":0}]