[{"revisionId":448878,"songId":487384,"description":"new","createdAt":"2021-07-05T15:32:57.000Z","source":"https://gp.songsterr.com/46204302.gp5","personId":2042842,"person":"can saral","title":"1.Solo","artist":"Yjs D#","tracksCount":2,"reports":[],"commentsCount":0},{"revisionId":448874,"songId":487384,"description":"Dist","createdAt":"2021-07-05T15:12:08.000Z","source":"https://gp.songsterr.com/46204102.gp5","personId":2042842,"person":"can saral","title":"1.Solo","artist":"Yjs D#","tracksCount":2,"reports":[],"commentsCount":0},{"revisionId":448871,"songId":487384,"description":"Initial revision","createdAt":"2021-07-05T14:49:57.000Z","source":"https://gp.songsterr.com/46203823.gp5","personId":2042842,"person":"can saral","title":"1.Solo","artist":"Yjs D#","tracksCount":2,"reports":[],"commentsCount":0}]