[{"revisionId":456334,"songId":490252,"description":"added name","createdAt":"2021-08-30T21:25:25.000Z","source":"https://gp.songsterr.com/46875270.gp5","personId":2194440,"person":"Corban","title":"Sunset","artist":"Nearly Nowhere","tracksCount":1,"reports":[],"commentsCount":0},{"revisionId":455997,"songId":490252,"description":"Put the wrong file in now Im fixing it","createdAt":"2021-08-28T21:40:59.000Z","source":"https://gp.songsterr.com/46848215.gp5","personId":2194440,"person":"Corban","title":"Sunset","artist":"Nearly Nowhere","tracksCount":1,"reports":[],"commentsCount":0},{"revisionId":455996,"songId":490252,"description":"More of the song added","createdAt":"2021-08-28T21:34:44.000Z","source":"https://gp.songsterr.com/46848187.gp5","personId":2194440,"person":"Corban","title":"Sunset","artist":"Nearly Nowhere","tracksCount":1,"reports":[],"commentsCount":0},{"revisionId":455992,"songId":490252,"description":"fix guitar again","createdAt":"2021-08-28T21:15:40.000Z","source":"https://gp.songsterr.com/46847988.gp5","personId":2194440,"person":"Corban","title":"Sunset","artist":"Nearly Nowhere","tracksCount":1,"reports":[],"commentsCount":0},{"revisionId":455991,"songId":490252,"description":"Changed Guitar","createdAt":"2021-08-28T21:11:22.000Z","source":"https://gp.songsterr.com/46847961.gp5","personId":2194440,"person":"Corban","title":"Sunset","artist":"Nearly Nowhere","tracksCount":1,"reports":[],"commentsCount":0},{"revisionId":454768,"songId":490252,"description":"Initial revision","createdAt":"2021-08-21T19:12:33.000Z","source":"https://gp.songsterr.com/46742208.gp5","personId":2194440,"person":"Corban","title":"Sunset","artist":"Nearly Nowhere","tracksCount":1,"reports":[],"commentsCount":0}]