[{"revisionId":468995,"songId":496988,"description":"juice wrld","createdAt":"2021-11-28T22:43:41.535Z","source":"https://gp.songsterr.com/48030138.gp5","personId":2204929,"person":"shig","title":"ohio (Score version)","artist":"Shrine","tracksCount":9,"reports":[],"commentsCount":0},{"revisionId":468871,"songId":496988,"description":"Initial revision","createdAt":"2021-11-27T21:55:47.698Z","source":"https://gp.songsterr.com/48018875.gp5","personId":2204929,"person":"shig","title":"ohio (Score version)","artist":"Shrine","tracksCount":9,"reports":[],"commentsCount":0}]