[{"revisionId":473834,"songId":497325,"description":"sex","createdAt":"2021-12-31T18:12:17.191Z","source":"https://gp.songsterr.com/48465900.gp4","personId":2094092,"person":"Cleaning Crew","title":"Bleed","artist":"Logan's Sun","tracksCount":5,"reports":[],"commentsCount":0},{"revisionId":470002,"songId":497325,"description":"sxe","createdAt":"2021-12-05T23:34:37.700Z","source":"https://gp.songsterr.com/48120280.gp4","personId":2094092,"person":"Cleaning Crew","title":"Bleed","artist":"Logan's Sun","tracksCount":5,"reports":[],"commentsCount":0},{"revisionId":469999,"songId":497325,"description":"sxe","createdAt":"2021-12-05T23:21:42.268Z","source":"https://gp.songsterr.com/48119865.gp4","personId":2094092,"person":"Cleaning Crew","title":"Bleed","artist":"Logan's Sun","tracksCount":5,"reports":[],"commentsCount":0},{"revisionId":469961,"songId":497325,"description":"sxe","createdAt":"2021-12-05T18:37:44.822Z","source":"https://gp.songsterr.com/48116559.gp4","personId":2094092,"person":"Cleaning Crew","title":"Bleed","artist":"Logan's Sun","tracksCount":5,"reports":[],"commentsCount":0},{"revisionId":469878,"songId":497325,"description":"ImageImageImageImageImageImageImageImageImageImageImageImageImageImageImageImageImageImageImageImageImage","createdAt":"2021-12-05T03:54:19.832Z","source":"https://gp.songsterr.com/48110223.gp4","personId":2094092,"person":"Cleaning Crew","title":"Bleed","artist":"Logan's Sun","tracksCount":5,"reports":[],"commentsCount":0},{"revisionId":469876,"songId":497325,"description":"Bleed","createdAt":"2021-12-05T03:40:23.388Z","source":"https://gp.songsterr.com/48109735.gp4","personId":2094092,"person":"Cleaning Crew","title":"Bleed","artist":"Logan's Sun","tracksCount":5,"reports":[],"commentsCount":0},{"revisionId":469874,"songId":497325,"description":"worm odyssey worm odyssey worm odyssey worm odyssey worm odyssey worm odyssey worm odyssey worm odyssey worm odyssey worm odyssey worm odyssey worm odyssey","createdAt":"2021-12-05T03:26:42.159Z","source":"https://gp.songsterr.com/48109611.gp4","personId":2094092,"person":"Cleaning Crew","title":"Bleed","artist":"Logan's Sun","tracksCount":5,"reports":[],"commentsCount":0},{"revisionId":469873,"songId":497325,"description":"sxexy","createdAt":"2021-12-05T03:19:21.386Z","source":"https://gp.songsterr.com/48109488.gp4","personId":2094092,"person":"Cleaning Crew","title":"Bleed","artist":"Logan's Sun","tracksCount":5,"reports":[],"commentsCount":0},{"revisionId":469872,"songId":497325,"description":"Bleed in my ass :3","createdAt":"2021-12-05T03:12:40.819Z","source":"https://gp.songsterr.com/48109365.gp4","personId":2094092,"person":"Cleaning Crew","title":"Bleed","artist":"Logan's Sun","tracksCount":5,"reports":[],"commentsCount":0},{"revisionId":469871,"songId":497325,"description":"sxe","createdAt":"2021-12-05T03:04:45.197Z","source":"https://gp.songsterr.com/48109242.gp4","personId":2094092,"person":"Cleaning Crew","title":"Bleed","artist":"Logan's Sun","tracksCount":5,"reports":[],"commentsCount":0},{"revisionId":469870,"songId":497325,"description":"Sex","createdAt":"2021-12-05T02:56:13.476Z","source":"https://gp.songsterr.com/48108817.gp4","personId":2094092,"person":"Cleaning Crew","title":"Bleed","artist":"Logan's Sun","tracksCount":5,"reports":[],"commentsCount":0},{"revisionId":469612,"songId":497325,"description":"sxe","createdAt":"2021-12-03T02:31:32.638Z","source":"https://gp.songsterr.com/48082867.gp4","personId":2094092,"person":"Cleaning Crew","title":"Bleed","artist":"Logan's Sun","tracksCount":5,"reports":[],"commentsCount":0},{"revisionId":469611,"songId":497325,"description":"sxe","createdAt":"2021-12-03T02:27:02.498Z","source":"https://gp.songsterr.com/48082743.gp4","personId":2094092,"person":"Cleaning Crew","title":"Bleed","artist":"Logan's Sun","tracksCount":5,"reports":[],"commentsCount":0},{"revisionId":469610,"songId":497325,"description":"sxe","createdAt":"2021-12-03T02:22:22.368Z","source":"https://gp.songsterr.com/48082620.gp4","personId":2094092,"person":"Cleaning Crew","title":"Bleed","artist":"Logan's Sun","tracksCount":5,"reports":[],"commentsCount":0},{"revisionId":469609,"songId":497325,"description":"balls","createdAt":"2021-12-03T02:15:12.141Z","source":"https://gp.songsterr.com/48082497.gp4","personId":2094092,"person":"Cleaning Crew","title":"Bleed","artist":"Logan's Sun","tracksCount":5,"reports":[],"commentsCount":0},{"revisionId":469607,"songId":497325,"description":"sex balls","createdAt":"2021-12-03T01:59:20.845Z","source":"https://gp.songsterr.com/48082275.gp4","personId":2094092,"person":"Cleaning Crew","title":"Bleed","artist":"Logan's Sun","tracksCount":5,"reports":[],"commentsCount":0},{"revisionId":469606,"songId":497325,"description":"sexysexysexy","createdAt":"2021-12-03T01:42:28.523Z","source":"https://gp.songsterr.com/48081861.gp4","personId":2094092,"person":"Cleaning Crew","title":"Bleed","artist":"Logan's Sun","tracksCount":5,"reports":[],"commentsCount":0},{"revisionId":469602,"songId":497325,"description":"sexyballs:3","createdAt":"2021-12-03T01:20:01.621Z","source":"https://gp.songsterr.com/48081277.gp4","personId":2094092,"person":"Cleaning Crew","title":"Bleed","artist":"Logan's Sun","tracksCount":5,"reports":[],"commentsCount":0},{"revisionId":469601,"songId":497325,"description":"Sexeyxeyxyex","createdAt":"2021-12-03T01:15:21.396Z","source":"https://gp.songsterr.com/48081154.gp4","personId":2094092,"person":"Cleaning Crew","title":"Bleed","artist":"Logan's Sun","tracksCount":5,"reports":[],"commentsCount":0},{"revisionId":469594,"songId":497325,"description":"Sex balls","createdAt":"2021-12-02T21:22:23.505Z","source":"https://gp.songsterr.com/48080150.gp4","personId":2094092,"person":"Cleaning Crew","title":"Bleed","artist":"Logan's Sun","tracksCount":4,"reports":[],"commentsCount":0},{"revisionId":469592,"songId":497325,"description":"Initial revision","createdAt":"2021-12-02T21:10:33.960Z","source":"https://gp.songsterr.com/48079952.gp4","personId":2094092,"person":"Cleaning Crew","title":"Bleed","artist":"Logan's Sun","tracksCount":5,"reports":[],"commentsCount":0}]