[{"revisionId":473209,"songId":499018,"description":"better articulations","createdAt":"2021-12-27T18:50:38.410Z","source":"https://gp.songsterr.com/48405912.gp5","personId":2150249,"person":"Berdy","title":"Tracing That Dream","artist":"Yoasobi","tracksCount":1,"reports":[],"commentsCount":0},{"revisionId":473205,"songId":499018,"description":"Initial revision","createdAt":"2021-12-27T18:43:13.076Z","source":"https://gp.songsterr.com/48405214.gp5","personId":2150249,"person":"Berdy","title":"Tracing That Dream","artist":"Yoasobi","tracksCount":1,"reports":[],"commentsCount":0}]