[{"revisionId":555140,"songId":500481,"description":"It is pop music and in the original song there's just another interval which I submit\r\n(via editor)","createdAt":"2023-03-15T20:53:50.000Z","source":"https://gp.songsterr.com/55858937.gp","personId":2553267,"person":"HHiK","title":"CADILLAC (RIFF)","artist":"Morgenshtern","tracksCount":1,"reports":[],"commentsCount":0},{"revisionId":476361,"songId":500481,"description":"Initial revision","createdAt":"2022-01-18T14:08:06.992Z","source":"https://gp.songsterr.com/48707054.gp5","personId":2327435,"person":"Arthur","title":"CADILLAC (RIFF)","artist":"Morgenshtern","tracksCount":1,"reports":[],"commentsCount":0}]