[{"revisionId":509754,"songId":503283,"description":"eagewrgerg","createdAt":"2022-08-21T18:02:21.121Z","source":"https://gp.songsterr.com/51838387.gp5","personId":2089066,"person":"Noah phillips","title":"King of the Dirt","artist":"Wooden People","tracksCount":9,"reports":[],"commentsCount":0},{"revisionId":501288,"songId":503283,"description":"rtjrtjrth","createdAt":"2022-07-06T17:18:43.290Z","source":"https://gp.songsterr.com/51038255.gp5","personId":2089066,"person":"Noah phillips","title":"King of the Dirt","artist":"Wooden People","tracksCount":9,"reports":[],"commentsCount":0},{"revisionId":490353,"songId":503283,"description":"sdgsdgvsdv","createdAt":"2022-04-24T17:11:51.144Z","source":"https://gp.songsterr.com/49989184.gp5","personId":2089066,"person":"Noah phillips","title":"King of the Dirt","artist":"Wooden People","tracksCount":9,"reports":[],"commentsCount":0},{"revisionId":482582,"songId":503283,"description":"Initial revision","createdAt":"2022-02-27T04:50:47.175Z","source":"https://gp.songsterr.com/49316508.gp5","personId":2089066,"person":"Noah phillips","title":"King of the Dirt","artist":"Wooden People","tracksCount":6,"reports":[],"commentsCount":0}]