[{"revisionId":483322,"songId":503653,"description":"corrected notes","createdAt":"2022-03-05T17:00:23.403Z","source":"https://gp.songsterr.com/49387521.gp5","personId":2345725,"person":"Deniz Kılıç","title":"Impossible Bassline","artist":"Davie504","tracksCount":3,"reports":[],"commentsCount":0},{"revisionId":483299,"songId":503653,"description":"Initial revision","createdAt":"2022-03-05T14:15:22.959Z","source":"https://gp.songsterr.com/49385376.gp5","personId":2345725,"person":"Deniz Kılıç","title":"Impossible Bassline","artist":"Davie504","tracksCount":3,"reports":[],"commentsCount":0}]