[{"revisionId":485661,"songId":503852,"description":"466344и","createdAt":"2022-03-21T11:33:44.368Z","source":"https://gp.songsterr.com/49593815.gp5","personId":2339218,"person":"Vlad","title":"Мутное небо","artist":"Вестник Смерти","tracksCount":3,"reports":[],"commentsCount":0},{"revisionId":485650,"songId":503852,"description":"ппппп77","createdAt":"2022-03-21T07:36:50.178Z","source":"https://gp.songsterr.com/49593197.gp5","personId":2339218,"person":"Vlad","title":"Мутное небо","artist":"Вестник Смерти","tracksCount":5,"reports":[],"commentsCount":0},{"revisionId":485543,"songId":503852,"description":"75745","createdAt":"2022-03-20T12:42:27.820Z","source":"https://gp.songsterr.com/49585536.gp5","personId":2339218,"person":"Vlad","title":"Мутное небо","artist":"Вестник Смерти","tracksCount":5,"reports":[],"commentsCount":0},{"revisionId":485295,"songId":503852,"description":"68845","createdAt":"2022-03-18T12:39:39.750Z","source":"https://gp.songsterr.com/49566096.gp5","personId":2339218,"person":"Vlad","title":"Мутное небо","artist":"Вестник Смерти","tracksCount":4,"reports":[],"commentsCount":0},{"revisionId":483839,"songId":503852,"description":"нш8666","createdAt":"2022-03-09T10:35:58.455Z","source":"https://gp.songsterr.com/49437649.gp5","personId":2339218,"person":"Vlad","title":"Мутное небо","artist":"Вестник Смерти","tracksCount":4,"reports":[],"commentsCount":0},{"revisionId":483709,"songId":503852,"description":"Initial revision","createdAt":"2022-03-08T07:03:49.667Z","source":"https://gp.songsterr.com/49423383.gp5","personId":2339218,"person":"Vlad","title":"Мутное небо","artist":"Вестник Смерти","tracksCount":4,"reports":[],"commentsCount":0}]