[{"revisionId":488066,"songId":505772,"description":"Guitar Pro 5","createdAt":"2022-04-06T21:38:47.749Z","source":"https://gp.songsterr.com/49780032.gp5","personId":2360940,"person":"Studio Work","title":"Menssagem de Amor","artist":"Paralamas Do Sucesso","tracksCount":7,"reports":[],"commentsCount":0},{"revisionId":488065,"songId":505772,"description":"Initial revision","createdAt":"2022-04-06T21:37:47.572Z","source":"https://gp.songsterr.com/49780031.gp5","personId":2360940,"person":"Studio Work","title":"Menssagem de Amor","artist":"Paralamas Do Sucesso","tracksCount":7,"reports":[],"commentsCount":0}]