[{"revisionId":488136,"songId":505805,"description":"fixed errors","createdAt":"2022-04-07T13:14:07.365Z","source":"https://gp.songsterr.com/49784697.gp5","personId":2361136,"person":"Массовые Мероприятия","title":"Бей! (вступление)","artist":"Массовые Мероприятия","tracksCount":4,"reports":[],"commentsCount":0},{"revisionId":488135,"songId":505805,"description":"Initial revision","createdAt":"2022-04-07T13:08:32.121Z","source":"https://gp.songsterr.com/49784598.gp5","personId":2361136,"person":"Массовые Мероприятия","title":"Бей! (вступление)","artist":"Массовые Мероприятия","tracksCount":4,"reports":[],"commentsCount":0}]