[{"revisionId":547945,"songId":507257,"description":"fix","createdAt":"2023-02-16T20:53:38.232Z","source":"https://gp.songsterr.com/55349389.gp","personId":2139566,"person":"Romition","title":"Fedos Lyverniy","artist":"Bass","tracksCount":5,"reports":[],"commentsCount":0},{"revisionId":491018,"songId":507257,"description":"Drum fix","createdAt":"2022-04-28T10:12:28.417Z","source":"https://gp.songsterr.com/50047295.gp5","personId":2139566,"person":"Romition","title":"Fedos Lyverniy","artist":"Bass","tracksCount":5,"reports":[],"commentsCount":0},{"revisionId":490959,"songId":507257,"description":"Initial revision","createdAt":"2022-04-28T07:13:45.420Z","source":"https://gp.songsterr.com/50041719.gp5","personId":2139566,"person":"Romition","title":"Fedos Lyverniy","artist":"Bass","tracksCount":5,"reports":[],"commentsCount":0}]