[{"revisionId":547935,"songId":514101,"description":"drum figs","createdAt":"2023-02-16T20:02:53.474Z","source":"https://gp.songsterr.com/55348370.gp5","personId":2313453,"person":"scrub dunkley","title":"Atmosphere","artist":"Lithium","tracksCount":4,"reports":[],"commentsCount":0},{"revisionId":545399,"songId":514101,"description":"pre chorus fix","createdAt":"2023-02-06T17:57:06.183Z","source":"https://gp.songsterr.com/55144137.gp5","personId":2313453,"person":"scrub dunkley","title":"Atmosphere","artist":"Lithium","tracksCount":4,"reports":[],"commentsCount":0},{"revisionId":545254,"songId":514101,"description":"chorus fix","createdAt":"2023-02-05T23:58:56.408Z","source":"https://gp.songsterr.com/55134006.gp5","personId":2313453,"person":"scrub dunkley","title":"Atmosphere","artist":"Lithium","tracksCount":4,"reports":[],"commentsCount":0},{"revisionId":518903,"songId":514101,"description":"bass fix","createdAt":"2022-10-10T16:20:57.952Z","source":"https://gp.songsterr.com/52729626.gp5","personId":2313453,"person":"scrub dunkley","title":"Atmosphere","artist":"Lithium","tracksCount":4,"reports":[],"commentsCount":0},{"revisionId":516399,"songId":514101,"description":"u rude","createdAt":"2022-09-27T11:16:02.863Z","source":"https://gp.songsterr.com/52488362.gp5","personId":2313453,"person":"scrub dunkley","title":"Atmosphere","artist":"Lithium","tracksCount":4,"reports":[],"commentsCount":0},{"revisionId":510151,"songId":514101,"description":"Scrub has got a lot of these initial revisions incredibly wrong, the bass was all one note too high, the chorus riff was wrong and the drums were mistabbed too.","createdAt":"2022-08-23T17:25:51.520Z","source":"https://gp.songsterr.com/51877667.gp5","personId":2415339,"person":"click123","title":"Atmosphere","artist":"Lithium","tracksCount":4,"reports":[],"commentsCount":0},{"revisionId":504625,"songId":514101,"description":"Initial revision","createdAt":"2022-07-23T12:48:08.721Z","source":"https://gp.songsterr.com/51368661.gp5","personId":2313453,"person":"scrub dunkley","title":"Atmosphere","artist":"Lithium","tracksCount":5,"reports":[],"commentsCount":0}]