[{"revisionId":522332,"songId":522733,"description":"added 16th notes","createdAt":"2022-10-30T06:15:49.047Z","source":"https://gp.songsterr.com/53070079.gp5","personId":2178147,"person":"Jim Poh Heah","title":"Better When I'm Dancin'","artist":"Kittymommy","tracksCount":16,"reports":[],"commentsCount":0},{"revisionId":522327,"songId":522733,"description":"updated rights and lefts","createdAt":"2022-10-30T05:48:43.429Z","source":"https://gp.songsterr.com/53069220.gp5","personId":2178147,"person":"Jim Poh Heah","title":"Better When I'm Dancin'","artist":"Kittymommy","tracksCount":16,"reports":[],"commentsCount":0},{"revisionId":522179,"songId":522733,"description":"Initial revision","createdAt":"2022-10-29T10:28:14.251Z","source":"https://gp.songsterr.com/53055403.gp5","personId":2178147,"person":"Jim Poh Heah","title":"Better When I'm Dancin'","artist":"Kittymommy","tracksCount":16,"reports":[],"commentsCount":0}]