[{"revisionId":530077,"songId":526620,"description":"Added Super fucking basic drums because the track sounded dry without them","createdAt":"2022-12-07T00:34:47.940Z","source":"https://gp.songsterr.com/53822959.gp5","personId":1975853,"person":"Zertwast","title":"Soldier","artist":"(Ugp)","tracksCount":6,"reports":[],"commentsCount":0},{"revisionId":530076,"songId":526620,"description":"Initial revision","createdAt":"2022-12-07T00:23:37.719Z","source":"https://gp.songsterr.com/53822718.gp5","personId":1975853,"person":"Zertwast","title":"Soldier","artist":"(Ugp)","tracksCount":5,"reports":[],"commentsCount":0}]