[{"revisionId":531370,"songId":527247,"description":"Removed lead guitar","createdAt":"2022-12-13T01:39:09.572Z","source":"https://gp.songsterr.com/53950413.gp5","personId":2334777,"person":"Timeless","title":"All Time Low (TEASER)","artist":"Shawn Cochran","tracksCount":5,"reports":[],"commentsCount":0},{"revisionId":531369,"songId":527247,"description":"Changed back bc dookie booty","createdAt":"2022-12-13T01:25:39.309Z","source":"https://gp.songsterr.com/53950096.gp5","personId":2334777,"person":"Timeless","title":"All Time Low (TEASER)","artist":"Shawn Cochran","tracksCount":6,"reports":[],"commentsCount":0},{"revisionId":531367,"songId":527247,"description":"Changed the last 2 bears before the chorus a bit","createdAt":"2022-12-13T01:22:09.239Z","source":"https://gp.songsterr.com/53949948.gp5","personId":2334777,"person":"Timeless","title":"All Time Low (TEASER)","artist":"Shawn Cochran","tracksCount":6,"reports":[],"commentsCount":0},{"revisionId":531276,"songId":527247,"description":"Initial revision","createdAt":"2022-12-12T18:26:56.018Z","source":"https://gp.songsterr.com/53940595.gp5","personId":2334777,"person":"Timeless","title":"All Time Low (TEASER)","artist":"Shawn Cochran","tracksCount":6,"reports":[],"commentsCount":0}]