[{"revisionId":545675,"songId":534200,"description":"Fixed errors","createdAt":"2023-02-07T17:54:18.986Z","source":"https://gp.songsterr.com/55166266.gp5","personId":2176556,"person":"Rexus752","title":"Vietnam","artist":"Post Nebbia","tracksCount":1,"reports":[],"commentsCount":0},{"revisionId":545642,"songId":534200,"description":"Fixed errors","createdAt":"2023-02-07T15:47:55.965Z","source":"https://gp.songsterr.com/55163161.gp5","personId":2176556,"person":"Rexus752","title":"Vietnam","artist":"Post Nebbia","tracksCount":1,"reports":[],"commentsCount":0},{"revisionId":545639,"songId":534200,"description":"Initial revision","createdAt":"2023-02-07T15:41:21.309Z","source":"https://gp.songsterr.com/55163036.gp","personId":2176556,"person":"Rexus752","title":"Vietnam","artist":"Post Nebbia","tracksCount":1,"reports":[],"commentsCount":0}]