[{"revisionId":564371,"songId":543501,"description":"dddddddddddd","createdAt":"2023-04-18T22:14:53.000Z","source":"https://gp.songsterr.com/56523613.gp5","personId":2254891,"person":"roland homie","title":"enene","artist":"Nez","tracksCount":1,"reports":[],"commentsCount":0},{"revisionId":564369,"songId":543501,"description":"asdasdasd","createdAt":"2023-04-18T22:01:30.000Z","source":"https://gp.songsterr.com/56523441.gp5","personId":2254891,"person":"roland homie","title":"enene","artist":"Nez","tracksCount":1,"reports":[],"commentsCount":0},{"revisionId":564347,"songId":543501,"description":"Initial revision","createdAt":"2023-04-18T20:22:32.000Z","source":"https://gp.songsterr.com/56520634.gp5","personId":2254891,"person":"roland homie","title":"enene","artist":"Nez","tracksCount":10,"reports":[],"commentsCount":0}]