[{"revisionId":579644,"songId":549385,"description":"bass add","createdAt":"2023-06-05T12:42:51.000Z","source":"https://gp.songsterr.com/57385642.gp5","personId":2413719,"person":"Mr Zero","title":"Binge and Рurge","artist":"Clutch","tracksCount":4,"reports":[],"commentsCount":0},{"revisionId":579624,"songId":549385,"description":"it's new version","createdAt":"2023-06-05T11:20:44.000Z","source":"https://gp.songsterr.com/57385405.gp5","personId":2413719,"person":"Mr Zero","title":"Binge and Рurge","artist":"Clutch","tracksCount":3,"reports":[],"commentsCount":0},{"revisionId":579619,"songId":549385,"description":"I will load a right version of this song","createdAt":"2023-06-05T11:13:00.000Z","source":"https://gp.songsterr.com/57385168.gp5","personId":2413719,"person":"Mr Zero","title":"Binge and Рurge","artist":"Clutch","tracksCount":3,"reports":[],"commentsCount":0},{"revisionId":579611,"songId":549385,"description":"Initial revision","createdAt":"2023-06-05T10:35:19.000Z","source":"https://gp.songsterr.com/57384776.gp5","personId":2413719,"person":"Mr Zero","title":"Binge and Рurge","artist":"Clutch","tracksCount":3,"reports":[],"commentsCount":0}]