[{"revisionId":608028,"songId":553175,"description":"Briefly explain your changes (fixed errors, replaces with whole new version, corrected tempo, etc)","createdAt":"2023-08-20T20:44:27.000Z","source":"https://gp.songsterr.com/59024481.gp5","personId":2353894,"person":"Banana Bunch","title":"Eruption (Tapping section transcribed for bass)","artist":"Van Halen","tracksCount":1,"reports":[],"commentsCount":0},{"revisionId":608023,"songId":553175,"description":"now just fixed something that didn't look good","createdAt":"2023-08-20T20:31:13.000Z","source":"https://gp.songsterr.com/59024206.gp5","personId":2353894,"person":"Banana Bunch","title":"Eruption (Tapping section transcribed for bass)","artist":"Van Halen","tracksCount":1,"reports":[],"commentsCount":0},{"revisionId":608021,"songId":553175,"description":"hopefully actually fixed what was wrong with the bend","createdAt":"2023-08-20T20:28:43.000Z","source":"https://gp.songsterr.com/59024180.gp5","personId":2353894,"person":"Banana Bunch","title":"Eruption (Tapping section transcribed for bass)","artist":"Van Halen","tracksCount":1,"reports":[],"commentsCount":0},{"revisionId":608020,"songId":553175,"description":"fixed what was wrong with the bend","createdAt":"2023-08-20T20:23:58.000Z","source":"https://gp.songsterr.com/59024155.gp5","personId":2353894,"person":"Banana Bunch","title":"Eruption (Tapping section transcribed for bass)","artist":"Van Halen","tracksCount":1,"reports":[],"commentsCount":0},{"revisionId":608019,"songId":553175,"description":"added more parts","createdAt":"2023-08-20T20:18:09.000Z","source":"https://gp.songsterr.com/59024130.gp5","personId":2353894,"person":"Banana Bunch","title":"Eruption (Tapping section transcribed for bass)","artist":"Van Halen","tracksCount":1,"reports":[],"commentsCount":0},{"revisionId":596421,"songId":553175,"description":"changed voice","createdAt":"2023-07-22T01:06:51.000Z","source":"https://gp.songsterr.com/58340378.gp5","personId":2353894,"person":"Banana Bunch","title":"Eruption (Tapping section transcribed for bass)","artist":"Van Halen","tracksCount":1,"reports":[],"commentsCount":0},{"revisionId":589860,"songId":553175,"description":"just added some notes","createdAt":"2023-07-04T17:48:52.000Z","source":"https://gp.songsterr.com/57972020.gp5","personId":2353894,"person":"Banana Bunch","title":"Eruption (Tapping section transcribed for bass)","artist":"Van Halen","tracksCount":1,"reports":[],"commentsCount":0},{"revisionId":589857,"songId":553175,"description":"Initial revision","createdAt":"2023-07-04T17:36:26.000Z","source":"https://gp.songsterr.com/57971871.gp5","personId":2353894,"person":"Banana Bunch","title":"Eruption (Tapping section transcribed for bass)","artist":"Van Halen","tracksCount":1,"reports":[],"commentsCount":0}]