[{"revisionId":644260,"songId":569210,"description":"Fixed","createdAt":"2023-11-23T21:32:31.136Z","source":"https://gp.songsterr.com/kraujja_1_3_new2.842833.gp5","personId":2334548,"person":"Mikas Blo탑is","title":"I","artist":"Kraujja","tracksCount":2,"reports":[],"commentsCount":0},{"revisionId":644256,"songId":569210,"description":"Fixed","createdAt":"2023-11-23T21:24:32.727Z","source":"https://gp.songsterr.com/kraujja_1_3_new2.228043.gp5","personId":2334548,"person":"Mikas Blo탑is","title":"I","artist":"Kraujja","tracksCount":2,"reports":[],"commentsCount":0},{"revisionId":644244,"songId":569210,"description":"All riffs","createdAt":"2023-11-23T21:12:53.717Z","source":"https://gp.songsterr.com/kraujja_1_3_new.122085.gp5","personId":2334548,"person":"Mikas Blo탑is","title":"I","artist":"Kraujja","tracksCount":2,"reports":[],"commentsCount":0},{"revisionId":631390,"songId":569210,"description":"Initial revision","createdAt":"2023-10-21T14:12:46.856Z","source":"https://gp.songsterr.com/kraujja_1.467983.gp5","personId":2334548,"person":"Mikas Blo탑is","title":"I","artist":"Kraujja","tracksCount":2,"reports":[],"commentsCount":0}]