[{"revisionId":635457,"songId":569635,"description":"outro + vocals fix","createdAt":"2023-11-02T16:42:44.514Z","source":"https://gp.songsterr.com/adrenaline__2._new_sologp.283094.gp","personId":2560685,"person":"eugenepk","title":"Adrenaline!","artist":"Casi","tracksCount":5,"reports":[],"commentsCount":0},{"revisionId":633116,"songId":569635,"description":"solo improved","createdAt":"2023-10-26T17:08:11.197Z","source":"https://gp.songsterr.com/adrenaline__2._new_sologp.871284.gp","personId":2560685,"person":"eugenepk","title":"Adrenaline!","artist":"Casi","tracksCount":5,"reports":[],"commentsCount":0},{"revisionId":632441,"songId":569635,"description":"fix","createdAt":"2023-10-24T18:45:19.063Z","source":"https://gp.songsterr.com/adrenaline__2.148925.gp","personId":2560685,"person":"eugenepk","title":"Adrenaline!","artist":"Casi","tracksCount":5,"reports":[],"commentsCount":0},{"revisionId":632433,"songId":569635,"description":"Initial revision","createdAt":"2023-10-24T18:34:31.356Z","source":"https://gp.songsterr.com/adrenaline__2.467063.gp","personId":2560685,"person":"eugenepk","title":"Adrenaline!","artist":"Casi","tracksCount":5,"reports":[],"commentsCount":0}]