[{"revisionId":633212,"songId":569743,"description":"Fixed a Whole part missing, and added the slight variation at the end.","createdAt":"2023-10-26T21:24:01.884Z","source":"https://gp.songsterr.com/leave_you_alone_sea_of_lettuce_bassv2.123256.gp5","personId":2381641,"person":"WiseG","title":"Leave You Alone","artist":"Sea Of Lettuce","tracksCount":1,"reports":[],"commentsCount":0},{"revisionId":632741,"songId":569743,"description":"Initial revision","createdAt":"2023-10-25T16:11:23.520Z","source":"https://gp.songsterr.com/leave_you_alone_sea_of_lettuce_bass.311754.gp5","personId":2381641,"person":"WiseG","title":"Leave You Alone","artist":"Sea Of Lettuce","tracksCount":1,"reports":[],"commentsCount":0}]