[{"revisionId":624296,"songId":64439,"description":"This now garbage website wont let me plat this track with backing audio unless I do this apparently.\r\n(via editor)","createdAt":"2023-10-01T18:35:44.000Z","source":"https://gp.songsterr.com/export.556890.gp","personId":2174521,"person":"Fuckthis","title":"Ocean Man","artist":"Ween","tracksCount":9,"reports":[{"kind":"errors","summary":""}],"commentsCount":0},{"revisionId":449647,"songId":64439,"description":"fixed one minor thing with the bass","createdAt":"2021-07-11T23:19:58.000Z","source":"https://gp.songsterr.com/46272489.gp5","personId":2232039,"person":"Jack","title":"Ocean Man","artist":"Ween","tracksCount":9,"reports":[],"commentsCount":0},{"revisionId":449646,"songId":64439,"description":"fixed my mistake of not ading the other instuments, sorry.","createdAt":"2021-07-11T23:18:11.000Z","source":"https://gp.songsterr.com/46272477.gp5","personId":2232039,"person":"Jack","title":"Ocean Man","artist":"Ween","tracksCount":9,"reports":[],"commentsCount":0},{"revisionId":410685,"songId":64439,"description":"Complete overhaul","createdAt":"2020-07-19T22:22:07.000Z","source":"https://gp.songsterr.com/42687230.gp5","personId":1738896,"person":"A Toaster Oven","title":"Ocean Man","artist":"Ween","tracksCount":9,"reports":[],"commentsCount":0},{"revisionId":369538,"songId":64439,"description":"Corrected and revised guitar leads. Extended tab to full length of the song. Added some section titles.","createdAt":"2019-02-02T18:58:45.000Z","source":"https://gp.songsterr.com/38794626.gp5","personId":551392,"person":"Steve","title":"Ocean Man","artist":"Ween","tracksCount":7,"reports":[],"commentsCount":0},{"revisionId":81254,"songId":64439,"description":"Initial revision","createdAt":"2011-01-01T19:48:47.000Z","source":"https://gp.songsterr.com/3719601.gp5","personId":112396,"person":"Abdallah","title":"Ocean Man","artist":"Ween","tracksCount":7,"reports":[],"commentsCount":0}]