[{"revisionId":593716,"songId":71278,"description":"missing solos\r\n(via editor)","createdAt":"2023-07-14T09:58:39.000Z","source":"https://gp.songsterr.com/58191059.gp","personId":2588131,"person":"Darr","title":"No Sacrifice No Victory","artist":"HammerFall","tracksCount":4,"reports":[],"commentsCount":0},{"revisionId":308339,"songId":71278,"description":"Initial revision","createdAt":"2016-11-06T06:11:50.000Z","source":"https://gp.songsterr.com/23319875.gp5","personId":145787,"person":"Leonard","title":"No Sacrifice No Victory","artist":"HammerFall","tracksCount":4,"reports":[],"commentsCount":0}]