[{"revisionId":611268,"songId":76883,"description":"added missing bars\r\n(via editor)","createdAt":"2023-08-29T13:10:43.000Z","source":"https://gp.songsterr.com/59179350.gp","personId":2587083,"person":"Vitgit","title":"Alive","artist":"Nekromantix","tracksCount":3,"reports":[],"commentsCount":0},{"revisionId":94813,"songId":76883,"description":"Initial revision","createdAt":"2011-03-08T22:47:55.000Z","source":"https://gp.songsterr.com/4096258.gp5","personId":156047,"person":"Mike","title":"Alive","artist":"Nekromantix","tracksCount":3,"reports":[],"commentsCount":0}]