[{"revisionId":372036,"songId":85476,"description":"added full band","createdAt":"2019-03-12T23:51:00.000Z","source":"https://gp.songsterr.com/39017353.gp5","personId":1213565,"person":"Chaz Chazington","title":"Marunouchi Sadistic","artist":"Shiina Ringo","tracksCount":6,"reports":[],"commentsCount":0},{"revisionId":261227,"songId":85476,"description":"marunochi sadistic","createdAt":"2015-11-18T16:32:13.000Z","source":"https://gp.songsterr.com/10471668.gp5","personId":1034702,"person":"Deleted user","title":"Marunouchi Sadistic","artist":"Shiina Ringo","tracksCount":1,"reports":[],"commentsCount":0}]